Workbook

Sheet Cover
C2: Valuation Analysis Report
C4: DCF Anlysis | Comparable Companies | Precendent Transactions | U4: Confidential | For Internal Use Only
C6: Targeted Company: RH
C7: Prepared By: Frey Guo
C8: Date: May 2026
C9: Version: 1.0
C13: Table of Contents | O13: Model Checks
C15: Dashboard | O15: Incorrect Date Set for Valuation? | U15: =IF('DCF Inputs'!M50>'DCF Inputs'!M51,"yes", "No") -> No
C16: Sensitivity Analysis | O16: Incorrect Date Set for First Cash Flow? | U16: =IF('DCF Inputs'!M51>'DCF Inputs'!M52,"Yes","No") -> No
C17: Input | O17: Terminal Growth Rate Greater Than or Equal To WACC? | U17: =IF('DCF Inputs'!G54<='DCF Inputs'!G52,"Yes","No") -> No
C18: DCF Model | O18: Unused Tax Losses Remaining? (Levered Schedule) | U18: =IF('DCF Model'!P161=0,"No","Yes") -> No
C19: Comparable Anlysis | O19: Unused Tax Losses Remaining? (Unlevered Schedule) | U19: =IF('DCF Model'!P194=0,"No","Yes") -> No
C20: Precendent Transactions | O20: Two UFCF Methods Different? | U20: =IF(SUM('DCF Model'!L215:Q215)=SUM('DCF Model'!L225:Q225),"No","Yes") -> No
C21: RH Fiancial Report
C28: Disclamer
C29: This valuation analysis has been prepared solely for career, academic, and internal discussion purposes. The information contained herein is based on publicly available data and assumptions believed to be reasonable at the time of preparation. This report does not constitute investment advice, a recommendation, or an offer to buy or sell any security. Actual results may differ materially from the estimates and projections presented.

Sheet Dashboard
B2: Projected Business Performance | O2: Data: Company Overview
O4: Company Information
B5: =CONCATENATE("Company Name: "&Q5) -> Company Name: RH | E5: =CONCATENATE("Recommendation: "&Q6) -> Recommendation: Hold | L5: =CONCATENATE("Target Price: "&Q7) -> Target Price: 173.21 | O5: Company Name | Q5: RH
O6: Recommendation | Q6: Hold
O7: Target Price | Q7: 173.21
C17: Valuation Summary: Football Field Chart
C43: Valuation Graphing Data
D45: Low | E45: Delta | F45: High | G45: Mid
C46: DCF Valuation Analysis | D46: ='DCF Sensitivity Analysis'!H14 -> 49.917683 | E46: =F46-D46 -> 238.00976 | F46: ='DCF Sensitivity Analysis'!H12 -> 287.92744 | G46: =D46+E46/2 -> 168.92256
C47: Comparable Trading Analysis | D47: =Comps!J29 -> 9.9286213 | E47: =F47-D47 -> 220.43367 | F47: =Comps!J28 -> 230.36229 | G47: =D47+E47/2 -> 120.14546
C48: Precedent Transaction Analysis | D48: =Transactions!M29 -> -2.6847844 | E48: =F48-D48 -> 294.58406 | F48: =Transactions!M28 -> 291.89927 | G48: =D48+E48/2 -> 144.60724
C49: 52-Week Trading | D49: 106.3 | E49: =F49-D49 -> 150.7 | F49: 257 | G49: =D49+E49/2 -> 181.65
C50: Consensus Research | D50: 88 | E50: =F50-D50 -> 187 | F50: 275 | G50: =D50+E50/2 -> 181.5

Sheet DCF Sensitivity Analysis
B3: Dashboard: Perpetuity Method
C5: Model Drivers Set To | D5: 2 | L5: All figures in USD MM unless stated
D7: Main Outputs 1 | L7: Selected Inputs
F9: Enterprise | G9: Equity | H9: Equity | L9: Terminal Growth Rate | O9: ='DCF Model'!C232 -> 0.025
F10: Value | G10: Value | H10: Per Share | L10: WACC | O10: ='DCF Model'!C233 -> 0.083031313
F11: ='DCF Model'!K258 -> 6900.4788 | L11: Net Debt | N11: (End of 2025) | O11: ='DCF Inputs'!M41 -> 3930
D12: Best Case | E12: 1 | F12: 9112.694 | G12: =F12-$O$11 -> 5182.694 | H12: =G12/$O$12 -> 287.92744 | L12: Shares Outstanding | N12: (mm) | O12: ='DCF Inputs'!G50 -> 18
D13: Base Case | E13: =E12+1 -> 2 | F13: 6900.4788 | G13: =F13-$O$11 -> 2970.4788 | H13: =G13/$O$12 -> 165.0266 | L13: Current Stock Price | N13: (US$/sh) | O13: ='DCF Inputs'!G51 -> 136.42
D14: Worst Case | E14: =E13+1 -> 3 | F14: 4828.5183 | G14: =F14-$O$11 -> 898.51829 | H14: =G14/$O$12 -> 49.917683
D16: Enterprise Value 1 | L16: Equity Value per Share
D18: Terminal Growth Rate | L18: Terminal Growth Rate
C19: ='DCF Model'!K259 -> 6898.2991 | D19: =E19-0.0025 -> 0.02 | E19: =F19-0.0025 -> 0.0225 | F19: =O9 -> 0.025 | G19: =F19+0.0025 -> 0.0275 | H19: =G19+0.0025 -> 0.03 | L19: =D19 -> 0.02 | M19: =E19 -> 0.0225 | N19: =F19 -> 0.025 | O19: =G19 -> 0.0275 | P19: =H19 -> 0.03
B20: WACC | C20: =C21-0.005 -> 0.073031313 | D20: ='DCF Model'!D315 -> 7754.815 | E20: ='DCF Model'!E315 -> 8097.8078 | F20: ='DCF Model'!F315 -> 8476.5056 | G20: ='DCF Model'!G315 -> 8896.7901 | H20: ='DCF Model'!H315 -> 9365.9092 | J20: WACC | K20: =C20 -> 0.073031313 | L20: =D31/$O$12 -> 212.48972 | M20: =E31/$O$12 -> 231.54488 | N20: =F31/$O$12 -> 252.58365 | O20: =G31/$O$12 -> 275.93278 | P20: =H31/$O$12 -> 301.99495
C21: =C22-0.005 -> 0.078031313 | D21: ='DCF Model'!D316 -> 7027.4825 | E21: ='DCF Model'!E316 -> 7307.3088 | F21: ='DCF Model'!F316 -> 7613.5182 | G21: ='DCF Model'!G316 -> 7950.0266 | H21: ='DCF Model'!H316 -> 8321.5651 | K21: =C21 -> 0.078031313 | L21: =D32/$O$12 -> 172.08236 | M21: =E32/$O$12 -> 187.62827 | N21: =F32/$O$12 -> 204.6399 | O21: =G32/$O$12 -> 223.33481 | P21: =H32/$O$12 -> 243.97584
C22: =O10 -> 0.083031313 | D22: ='DCF Model'!D317 -> 6416.6971 | E22: ='DCF Model'!E317 -> 6648.5977 | F22: ='DCF Model'!F317 -> 6900.4788 | G22: ='DCF Model'!G317 -> 7175.0392 | H22: ='DCF Model'!H317 -> 7475.4862 | K22: =C22 -> 0.083031313 | L22: =D33/$O$12 -> 138.14984 | M22: =E33/$O$12 -> 151.0332 | N22: =F33/$O$12 -> 165.0266 | O22: =G33/$O$12 -> 180.27996 | P22: =H33/$O$12 -> 196.97146
C23: =C22+0.005 -> 0.088031313 | D23: ='DCF Model'!D318 -> 5896.7339 | E23: ='DCF Model'!E318 -> 6091.4796 | F23: ='DCF Model'!F318 -> 6301.6736 | G23: ='DCF Model'!G318 -> 6529.23 | H23: ='DCF Model'!H318 -> 6776.3927 | K23: =C23 -> 0.088031313 | L23: =D34/$O$12 -> 109.263 | M23: =E34/$O$12 -> 120.0822 | N23: =F34/$O$12 -> 131.75964 | O23: =G34/$O$12 -> 144.40167 | P23: =H34/$O$12 -> 158.13293
C24: =C23+0.005 -> 0.093031313 | D24: ='DCF Model'!D319 -> 5448.9135 | E24: ='DCF Model'!E319 -> 5614.3227 | F24: ='DCF Model'!F319 -> 5791.8886 | G24: ='DCF Model'!G319 -> 5983.0027 | H24: ='DCF Model'!H319 -> 6189.2771 | K24: =C24 -> 0.093031313 | L24: =D35/$O$12 -> 84.384086 | M24: =E35/$O$12 -> 93.573481 | N24: =F35/$O$12 -> 103.43826 | O24: =G35/$O$12 -> 114.05571 | P24: =H35/$O$12 -> 125.51539
D27: Equity Value | L27: Premium (Discount) to Stock Price
D29: Terminal Growth Rate | L29: Terminal Growth Rate
D30: =D19 -> 0.02 | E30: =E19 -> 0.0225 | F30: =F19 -> 0.025 | G30: =G19 -> 0.0275 | H30: =H19 -> 0.03 | L30: =D30 -> 0.02 | M30: =E30 -> 0.0225 | N30: =F30 -> 0.025 | O30: =G30 -> 0.0275 | P30: =H30 -> 0.03
B31: WACC | C31: =C20 -> 0.073031313 | D31: =D20-$O$11 -> 3824.815 | E31: =E20-$O$11 -> 4167.8078 | F31: =F20-$O$11 -> 4546.5056 | G31: =G20-$O$11 -> 4966.7901 | H31: =H20-$O$11 -> 5435.9092 | J31: WACC | K31: =C31 -> 0.073031313 | L31: =L20/$O$13-1 -> 0.55761415 | M31: =M20/$O$13-1 -> 0.69729421 | N31: =N20/$O$13-1 -> 0.85151479 | O31: =O20/$O$13-1 -> 1.022671 | P31: =P20/$O$13-1 -> 1.2137147
C32: =C21 -> 0.078031313 | D32: =D21-$O$11 -> 3097.4825 | E32: =E21-$O$11 -> 3377.3088 | F32: =F21-$O$11 -> 3683.5182 | G32: =G21-$O$11 -> 4020.0266 | H32: =H21-$O$11 -> 4391.5651 | K32: =C32 -> 0.078031313 | L32: =L21/$O$13-1 -> 0.26141592 | M32: =M21/$O$13-1 -> 0.37537213 | N32: =N21/$O$13-1 -> 0.50007258 | O32: =O21/$O$13-1 -> 0.63711195 | P32: =P21/$O$13-1 -> 0.78841695
C33: =C22 -> 0.083031313 | D33: =D22-$O$11 -> 2486.6971 | E33: =E22-$O$11 -> 2718.5977 | F33: =F22-$O$11 -> 2970.4788 | G33: =G22-$O$11 -> 3245.0392 | H33: =H22-$O$11 -> 3545.4862 | K33: =C33 -> 0.083031313 | L33: =L22/$O$13-1 -> 0.012680257 | M33: =M22/$O$13-1 -> 0.10711922 | N33: =N22/$O$13-1 -> 0.20969508 | O33: =O22/$O$13-1 -> 0.32150679 | P33: =P22/$O$13-1 -> 0.44386055
C34: =C23 -> 0.088031313 | D34: =D23-$O$11 -> 1966.7339 | E34: =E23-$O$11 -> 2161.4796 | F34: =F23-$O$11 -> 2371.6736 | G34: =G23-$O$11 -> 2599.23 | H34: =H23-$O$11 -> 2846.3927 | K34: =C34 -> 0.088031313 | L34: =L23/$O$13-1 -> -0.19906908 | M34: =M23/$O$13-1 -> -0.11976104 | N34: =N23/$O$13-1 -> -0.034161828 | O34: =O23/$O$13-1 -> 0.058508035 | P34: =P23/$O$13-1 -> 0.15916237
C35: =C24 -> 0.093031313 | D35: =D24-$O$11 -> 1518.9135 | E35: =E24-$O$11 -> 1684.3227 | F35: =F24-$O$11 -> 1861.8886 | G35: =G24-$O$11 -> 2053.0027 | H35: =H24-$O$11 -> 2259.2771 | K35: =C35 -> 0.093031313 | L35: =L24/$O$13-1 -> -0.38143904 | M35: =M24/$O$13-1 -> -0.31407799 | N35: =N24/$O$13-1 -> -0.24176619 | O35: =O24/$O$13-1 -> -0.16393705 | P35: =P24/$O$13-1 -> -0.079934068
P37: These tables require the workbook calculation to be set to automatic to update.
B40: Dashboard: Multiple Method
C42: Model Drivers Set To | D42: =D5 -> 2 | L42: All figures in USD MM unless stated
D44: Main Outputs 2 | L44: Main Outputs 1
F46: Enterprise | G46: Equity | H46: Equity | L46: Terminal Multiple | O46: ='DCF Inputs'!G53 -> 9
F47: Value | G47: Value | H47: Per Share | L47: WACC | O47: =O10 -> 0.083031313
F48: ='DCF Model'!K300 -> 6189.4224 | L48: Net Debt | N48: =N11 -> (End of 2025) | O48: =O11 -> 3930
D49: Best Case | E49: 1 | F49: 7724.9797 | G49: =F49-$O$48 -> 3794.9797 | H49: =G49/$O$49 -> 210.83221 | L49: Shares Outstanding | N49: (mm) | O49: =O12 -> 18
D50: Base Case | E50: 2 | F50: 6189.4224 | G50: =F50-$O$48 -> 2259.4224 | H50: =G50/$O$49 -> 125.52347 | L50: Current Stock Price | N50: (US$/sh) | O50: =O13 -> 136.42
D51: Worst Case | E51: 3 | F51: 4743.8182 | G51: =F51-$O$48 -> 813.81816 | H51: =G51/$O$49 -> 45.21212
D53: Enterprise Value 2 | L53: Equity Value per Share
D55: Terminal Multiple | L55: Terminal Multiple
C56: ='DCF Model'!K301 -> 6187.4714 | D56: =E56-0.5 -> 8 | E56: =F56-0.5 -> 8.5 | F56: =O46 -> 9 | G56: =+F56+0.5 -> 9.5 | H56: =+G56+0.5 -> 10 | L56: =D56 -> 8 | M56: =E56 -> 8.5 | N56: =F56 -> 9 | O56: =G56 -> 9.5 | P56: =H56 -> 10
B57: WACC | C57: =C20 -> 0.073031313 | D57: ='DCF Model'!L315 -> 5903.326 | E57: ='DCF Model'!M315 -> 6199.4904 | F57: ='DCF Model'!N315 -> 6495.6548 | G57: ='DCF Model'!O315 -> 6791.8192 | H57: ='DCF Model'!P315 -> 7087.9836 | J57: WACC | K57: =C57 -> 0.073031313 | L57: =D68/$O$49 -> 109.62922 | M57: =E68/$O$49 -> 126.0828 | N57: =F68/$O$49 -> 142.53638 | O57: =G68/$O$49 -> 158.98996 | P57: =H68/$O$49 -> 175.44353
C58: =C21 -> 0.078031313 | D58: ='DCF Model'!L316 -> 5763.1664 | E58: ='DCF Model'!M316 -> 6051.7126 | F58: ='DCF Model'!N316 -> 6340.2588 | G58: ='DCF Model'!O316 -> 6628.805 | H58: ='DCF Model'!P316 -> 6917.3512 | K58: =C58 -> 0.078031313 | L58: =D69/$O$49 -> 101.84258 | M58: =E69/$O$49 -> 117.87292 | N58: =F69/$O$49 -> 133.90327 | O58: =G69/$O$49 -> 149.93361 | P58: =H69/$O$49 -> 165.96396
C59: =C22 -> 0.083031313 | D59: ='DCF Model'!L317 -> 5627.1067 | E59: ='DCF Model'!M317 -> 5908.2645 | F59: ='DCF Model'!N317 -> 6189.4224 | G59: ='DCF Model'!O317 -> 6470.5802 | H59: ='DCF Model'!P317 -> 6751.7381 | K59: =C59 -> 0.083031313 | L59: =D70/$O$49 -> 94.283703 | M59: =E70/$O$49 -> 109.90358 | N59: =F70/$O$49 -> 125.52347 | O59: =G70/$O$49 -> 141.14335 | P59: =H70/$O$49 -> 156.76323
C60: =C23 -> 0.088031313 | D60: ='DCF Model'!L318 -> 5495.0074 | E60: ='DCF Model'!M318 -> 5768.9988 | F60: ='DCF Model'!N318 -> 6042.9903 | G60: ='DCF Model'!O318 -> 6316.9817 | H60: ='DCF Model'!P318 -> 6590.9731 | K60: =C60 -> 0.088031313 | L60: =D71/$O$49 -> 86.944856 | M60: =E71/$O$49 -> 102.1666 | N60: =F71/$O$49 -> 117.38835 | O60: =G71/$O$49 -> 132.61009 | P60: =H71/$O$49 -> 147.83184
C61: =C24 -> 0.093031313 | D61: ='DCF Model'!L319 -> 5366.7346 | E61: ='DCF Model'!M319 -> 5633.7739 | F61: ='DCF Model'!N319 -> 5900.8132 | G61: ='DCF Model'!O319 -> 6167.8525 | H61: ='DCF Model'!P319 -> 6434.8918 | K61: =C61 -> 0.093031313 | L61: =D72/$O$49 -> 79.818591 | M61: =E72/$O$49 -> 94.654106 | N61: =F72/$O$49 -> 109.48962 | O61: =G72/$O$49 -> 124.32514 | P61: =H72/$O$49 -> 139.16065
D64: Equity Value | L64: Premium (Discount) to Stock Price
D66: Terminal Multiple | L66: Terminal Multiple
D67: =D56 -> 8 | E67: =E56 -> 8.5 | F67: =F56 -> 9 | G67: =G56 -> 9.5 | H67: =H56 -> 10 | L67: =D67 -> 8 | M67: =E67 -> 8.5 | N67: =F67 -> 9 | O67: =G67 -> 9.5 | P67: =H67 -> 10
B68: WACC | C68: =C57 -> 0.073031313 | D68: =D57-$O$48 -> 1973.326 | E68: =E57-$O$48 -> 2269.4904 | F68: =F57-$O$48 -> 2565.6548 | G68: =G57-$O$48 -> 2861.8192 | H68: =H57-$O$48 -> 3157.9836 | J68: WACC | K68: =C68 -> 0.073031313 | L68: =L57/$O$50-1 -> -0.19638455 | M68: =M57/$O$50-1 -> -0.075774826 | N68: =N57/$O$50-1 -> 0.044834898 | O68: =O57/$O$50-1 -> 0.16544462 | P68: =P57/$O$50-1 -> 0.28605434
C69: =C58 -> 0.078031313 | D69: =D58-$O$48 -> 1833.1664 | E69: =E58-$O$48 -> 2121.7126 | F69: =F58-$O$48 -> 2410.2588 | G69: =G58-$O$48 -> 2698.805 | H69: =H58-$O$48 -> 2987.3512 | K69: =C69 -> 0.078031313 | L69: =L58/$O$50-1 -> -0.253463 | M69: =M58/$O$50-1 -> -0.13595571 | N69: =N58/$O$50-1 -> -0.018448418 | O69: =O58/$O$50-1 -> 0.099058873 | P69: =P58/$O$50-1 -> 0.21656616
C70: =C59 -> 0.083031313 | D70: =D59-$O$48 -> 1697.1067 | E70: =E59-$O$48 -> 1978.2645 | F70: =F59-$O$48 -> 2259.4224 | G70: =G59-$O$48 -> 2540.5802 | H70: =H59-$O$48 -> 2821.7381 | K70: =C70 -> 0.083031313 | L70: =L59/$O$50-1 -> -0.30887184 | M70: =M59/$O$50-1 -> -0.19437337 | N70: =N59/$O$50-1 -> -0.079874904 | O70: =O59/$O$50-1 -> 0.034623565 | P70: =P59/$O$50-1 -> 0.14912203
C71: =C60 -> 0.088031313 | D71: =D60-$O$48 -> 1565.0074 | E71: =E60-$O$48 -> 1838.9988 | F71: =F60-$O$48 -> 2112.9903 | G71: =G60-$O$48 -> 2386.9817 | H71: =H60-$O$48 -> 2660.9731 | K71: =C71 -> 0.088031313 | L71: =L60/$O$50-1 -> -0.36266782 | M71: =M60/$O$50-1 -> -0.2510878 | N71: =N60/$O$50-1 -> -0.13950778 | O71: =O60/$O$50-1 -> -0.027927765 | P71: =P60/$O$50-1 -> 0.083652255
C72: =C61 -> 0.093031313 | D72: =D61-$O$48 -> 1436.7346 | E72: =E61-$O$48 -> 1703.7739 | F72: =F61-$O$48 -> 1970.8132 | G72: =G61-$O$48 -> 2237.8525 | H72: =H61-$O$48 -> 2504.8918 | K72: =C72 -> 0.093031313 | L72: =L61/$O$50-1 -> -0.41490551 | M72: =M61/$O$50-1 -> -0.30615668 | N72: =N61/$O$50-1 -> -0.19740784 | O72: =O61/$O$50-1 -> -0.088659013 | P72: =P61/$O$50-1 -> 0.020089818
P74: These tables require the workbook calculation to be set to automatic to update.

Sheet DCF Inputs
C2: Drivers
C4: Driver Switcher | D4: ='DCF Sensitivity Analysis'!$D$5 -> 2
G5: 2026 | H5: =G5+1 -> 2027 | I5: =H5+1 -> 2028 | J5: =I5+1 -> 2029 | K5: =J5+1 -> 2030 | L5: Terms
C7: Revenue Growth | G7: =CHOOSE($D$4,G9,G10,G11) -> 0.05 | H7: =CHOOSE($D$4,H9,H10,H11) -> 0.04 | I7: =CHOOSE($D$4,I9,I10,I11) -> 0.035 | J7: =CHOOSE($D$4,J9,J10,J11) -> 0.035 | K7: =CHOOSE($D$4,K9,K10,K11) -> 0.05 | L7: =CHOOSE($D$4,L9,L10,L11) -> 0.05
C9: Best Case | G9: 0.06 | H9: 0.05 | I9: 0.045 | J9: 0.045 | K9: 0.06 | L9: 0.06
C10: Base Case | G10: 0.05 | H10: 0.04 | I10: 0.035 | J10: 0.035 | K10: 0.05 | L10: 0.05
C11: Worst Case | G11: 0.04 | H11: 0.03 | I11: 0.025 | J11: 0.025 | K11: 0.04 | L11: 0.04
C14: COGS % of Revenue | G14: =CHOOSE($D$4,G16,G17,G18) -> 0.555 | H14: =CHOOSE($D$4,H16,H17,H18) -> 0.553 | I14: =CHOOSE($D$4,I16,I17,I18) -> 0.55 | J14: =CHOOSE($D$4,J16,J17,J18) -> 0.548 | K14: =CHOOSE($D$4,K16,K17,K18) -> 0.545 | L14: =CHOOSE($D$4,L16,L17,L18) -> 0.5225
C16: Best Case | G16: 0.54 | H16: 0.538 | I16: 0.535 | J16: 0.533 | K16: 0.53 | L16: 0.5075
C17: Base Case | G17: 0.555 | H17: 0.553 | I17: 0.55 | J17: 0.548 | K17: 0.545 | L17: 0.5225
C18: Worst Case | G18: 0.57 | H18: 0.568 | I18: 0.565 | J18: 0.563 | K18: 0.56 | L18: 0.5375
C20: CapEx % of Revenue | G20: =CHOOSE($D$4,G22,G23,G24) -> 0.06 | H20: =CHOOSE($D$4,H22,H23,H24) -> 0.058 | I20: =CHOOSE($D$4,I22,I23,I24) -> 0.055 | J20: =CHOOSE($D$4,J22,J23,J24) -> 0.053 | K20: =CHOOSE($D$4,K22,K23,K24) -> 0.05 | L20: =CHOOSE($D$4,L22,L23,L24) -> 0.047
C22: Best Case | G22: 0.055 | H22: 0.053 | I22: 0.05 | J22: 0.048 | K22: 0.045 | L22: 0.042
C23: Base Case | G23: 0.06 | H23: 0.058 | I23: 0.055 | J23: 0.053 | K23: 0.05 | L23: 0.047
C24: Worst Case | G24: 0.065 | H24: 0.063 | I24: 0.06 | J24: 0.058 | K24: 0.055 | L24: 0.052
C26: Inflation | G26: 0.027 | H26: 0.025 | I26: 0.02 | J26: 0.02 | K26: 0.02 | L26: 0.015
C28: Working Capital
C29: Accounts Receivable | D29: (Days) | G29: 10 | H29: 10 | I29: 10 | J29: 10 | K29: 10 | L29: 10
C30: Inventory | D30: (Days) | G30: 150 | H30: 150 | I30: 150 | J30: 150 | K30: 150 | L30: 150
C31: Accounts Payable | D31: (Days) | G31: 45 | H31: 45 | I31: 45 | J31: 45 | K31: 45 | L31: 45
C32: prepaids % SG&A | G32: 0.025 | H32: 0.025 | I32: 0.025 | J32: 0.025 | K32: 0.025 | L32: 0.025
C33: other operating Assets & Revenue | G33: 0.012 | H33: 0.012 | I33: 0.012 | J33: 0.012 | K33: 0.012 | L33: 0.012
C34: Accrued Payroll % SG&A | G34: 0.02 | H34: 0.02 | I34: 0.02 | J34: 0.02 | K34: 0.02 | L34: 0.02
C35: Deferred Revenue (Current) % Revenue | G35: 0.1 | H35: 0.1 | I35: 0.1 | J35: 0.1 | K35: 0.1 | L35: 0.1
C36: Other Current Liabilities & Revenue | G36: 0.05 | H36: 0.05 | I36: 0.05 | J36: 0.05 | K36: 0.05 | L36: 0.05
C38: Other inputs
C40: Other inputs | I40: End of 2025 Balances
C41: Projected Interest Expense | G41: 200 | I41: Net Debt | M41: ='RH Financial Report'!H41 -> 3930
C42: First Year Tax Depreciation | G42: 0.5 | I42: Property Plant & Equipment | M42: ='RH Financial Report'!H27 -> 3110
C43: Blended Tax Depreciation Rate | G43: 0.1 | I43: Tax Basis for PP&E | M43: 704.956
C44: First Year Accounting Depreciation | G44: 0.4 | I44: Tax Losses | M44: 35.02
C45: Useful Life: Existing Assets | F45: (Years) | G45: 16
C46: Useful Life: New Assets | F46: (Years) | G46: 20
C47: Tax Rate | G47: 0.24
C49: Valuation | I49: Dates
C50: Shares Outstanding | F50: (mm) | G50: 18 | I50: Valuation Date | L50: (YY-MM-DD) | M50: 46164
C51: Current Stock Price | F51: (US$/sh) | G51: 136.42 | I51: First Expected Cash Flow | L51: (YY-MM-DD) | M51: 46203
C52: Terminal Growth Rate | G52: 0.025 | I52: First Fiscal Year End for Forecast | L52: (YY-MM-DD) | M52: 46387
C53: Terminal EBITDA Multiple 1 | G53: 9 | I53: First Year of Forecast | L53: (YYYY) | M53: =YEAR(M52) -> 2026
C54: Weighted Average Cost of Capital (WACC) | G54: =M96 -> 0.083031313 | I54: Incorrect Date Set for Valuation? | M54: =IF(M50>M51,1,0) -> 0
C55: Terminal Growth Greater Than or Equal To WACC? | G55: =IF(G52<=G54,0,1) -> 0 | I55: Incorrect Date Set for First Cash Flow? | M55: =IF(M51>M52,1,0) -> 0
I56: Days in Period | M56: 365
C58: Weighted Average Cost of Capital
I59: Average | J59: Debt/ | K59: Debt/ | L59: Levered | M59: Unlevered
C60: Name | D60: Ticker | E60: Region | G60: Debt | H60: Equity | I60: Tax Rate 1 | J60: Equity | K60: Capital | L60: Beta 2 | M60: Beta 3
C62: Arhaus | D62: ARHS | E62: U.S. | G62: 580.58 | H62: 418.23 | I62: 0.26 | J62: =G62/H62 -> 1.3881835 | K62: =G62/(G62+H62) -> 0.58127171 | L62: 2.42 | M62: =L62/(1+(1-I62)*J62) -> 1.1937319
C63: Williams-Sonoma | D63: WSM | E63: U.S. | G63: 1461.36 | H63: 2080 | I63: 0.25 | J63: =G63/H63 -> 0.70257692 | K63: =G63/(G63+H63) -> 0.41265503 | L63: 1.23 | M63: =L63/(1+(1-I63)*J63) -> 0.80553649
C64: Ethan Allen Interiors | D64: ETD | E64: U.S. | G64: 124.35 | H64: 482.27 | I64: 0.24 | J64: =G64/H64 -> 0.25784312 | K64: =G64/(G64+H64) -> 0.2049883 | L64: 1.04 | M64: =L64/(1+(1-I64)*J64) -> 0.86959374
C65: La-Z-Boy | D65: LZB | E65: U.S. | G65: 490.86 | H65: 1030 | I65: 0.25 | J65: =G65/H65 -> 0.47656311 | K65: =G65/(G65+H65) -> 0.3227516 | L65: 1.26 | M65: =L65/(1+(1-I65)*J65) -> 0.9282299
C66: Haverty Furniture | D66: HVT | E66: U.S. | G66: 216.42 | H66: 307.93 | I66: 0.26 | J66: =G66/H66 -> 0.70282207 | K66: =G66/(G66+H66) -> 0.41273958 | L66: 1.49 | M66: =L66/(1+(1-I66)*J66) -> 0.9802062
C67: MillerKnoll | D67: MLKN | E67: U.S. | G67: 1810 | H67: 1340 | I67: 0.24 | J67: =G67/H67 -> 1.3507463 | K67: =G67/(G67+H67) -> 0.57460317 | L67: 1.16 | M67: =L67/(1+(1-I67)*J67) -> 0.57239652
C68: Hooker Furnishings | D68: HOFT | E68: U.S. | G68: 28.14 | H68: 169.24 | I68: 0.24 | J68: =G68/H68 -> 0.16627275 | K68: =G68/(G68+H68) -> 0.14256764 | L68: 0.77 | M68: =L68/(1+(1-I68)*J68) -> 0.6836136
C69: Leggett & Platt | D69: LEG | E69: U.S. | G69: 1660 | H69: 1020 | I69: 0.23 | J69: =G69/H69 -> 1.627451 | K69: =G69/(G69+H69) -> 0.61940299 | L69: 1.41 | M69: =L69/(1+(1-I69)*J69) -> 0.6257941
C70: Bassett Furniture Industries | D70: BSET | E70: U.S. | G70: 89.39 | H70: 165.11 | I70: 0.24 | J70: =G70/H70 -> 0.54139664 | K70: =G70/(G70+H70) -> 0.35123772 | L70: 0.74 | M70: =L70/(1+(1-I70)*J70) -> 0.52427929
H72: Average | I72: =AVERAGE(I62:I70) -> 0.24555556 | J72: =AVERAGE(J62:J70) -> 0.80153949 | K72: =AVERAGE(K62:K70) -> 0.40246864 | L72: =AVERAGE(L62:L65) -> 1.4875 | M72: =AVERAGE(M62:M70) -> 0.79815353
H73: Median | I73: =MEDIAN(I62:I65) -> 0.25 | J73: =MEDIAN(J62:J65) -> 0.58957001 | K73: =MEDIAN(K62:K65) -> 0.36770331 | L73: =MEDIAN(L62:L65) -> 1.245 | M73: =MEDIAN(M62:M65) -> 0.89891182
C75: Risk Premium for Equity | I75: Cost of Equity
C77: Market Risk Premium | G77: 0.047 | I77: Risk Free Rate | M77: 0.046
C78: Average Unlevered Beta | G78: =M72 -> 0.79815353 | I78: Equity Risk Premium | M78: =G80 -> 0.080278282
C79: Levered Beta 4 | G79: =G78*(1+(1-M85)*G89) -> 1.7080486 | I79: Country Risk Premium | M79: 0.0015
C80: Equity Risk Premium | G80: =G79*G77 -> 0.080278282 | I80: Cost of Equity | M80: =SUM(M77:M79) -> 0.12777828
C82: Capital Structure | I82: Cost of Debt
F84: Current | G84: Target | I84: Pre-Tax Cost of Debt | M84: 0.07
C85: Total Debt | E85: ='RH Financial Report'!H40 -> 3970 | F85: =E85/E87 -> 0.60610687 | G85: 0.6 | I85: Tax Rate | M85: ='DCF Inputs'!G47 -> 0.24
C86: Market Capitalization | E86: 2580 | F86: =E86/E87 -> 0.39389313 | G86: =1-G85 -> 0.4 | I86: After-Tax Cost of Debt | M86: =M84*(1-M85) -> 0.0532
C87: Total Capitalization | E87: =SUM(E85:E86) -> 6550 | F87: =SUM(F85:F86) -> 1 | G87: =SUM(G85:G86) -> 1
C89: Debt / Equity | F89: =F85/F86 -> 1.5387597 | G89: =G85/G86 -> 1.5 | I89: Weighted Average Cost of Capital
L91: Weight | M91: Cost
C92: Tax Rate is a 5-Year Average. | I92: Debt Capital | L92: =G85 -> 0.6 | M92: =M86 -> 0.0532
C93: Levered beta is based on 5-year monthly data. | I93: Equity Capital | L93: =G86 -> 0.4 | M93: =M80 -> 0.12777828
C94: Unlevered Beta = Levered Beta / (1 + (1 - Tax Rate) × Debt-to-Equity)
C95: Levered Beta = Unlevered Beta x (1 + (1 - Tax rate) x (Debt-to-Equity))
I96: Weighted Average Cost of Capital | M96: =SUMPRODUCT(L92:L93,M92:M93) -> 0.083031313

Sheet DCF Model
B2: Revenue/COGOS Schedules
B4: All figures in USD mm unless stated | F4: 2020 | G4: =F4+1 -> 2021 | H4: =G4+1 -> 2022 | I4: =H4+1 -> 2023 | J4: =I4+1 -> 2024 | K4: =J4+1 -> 2025 | L4: =K4+1 -> 2026 | M4: =L4+1 -> 2027 | N4: =M4+1 -> 2028 | ... P4: =O4+1 -> 2030 | Q4: Terms
B6: Revenue Growth | G6: 0.31929825 | H6: -0.045212766 | I6: -0.15598886 | J6: 0.04950495 | K6: 0.081761006 | L6: ='DCF Inputs'!G7 -> 0.05 | M6: ='DCF Inputs'!H7 -> 0.04 | N6: ='DCF Inputs'!I7 -> 0.035 | O6: ='DCF Inputs'!J7 -> 0.035 | P6: ='DCF Inputs'!K7 -> 0.05 | Q6: ='DCF Inputs'!L7 -> 0.05
B7: Revenue | F7: 2850 | G7: 3760 | H7: 3590 | I7: 3030 | J7: 3180 | K7: 3440 | L7: =K7*(1+L6) -> 3612 | M7: =L7*(1+M6) -> 3756.48 | N7: =M7*(1+N6) -> 3887.9568 | O7: =N7*(1+O6) -> 4024.0353 | P7: =O7*(1+P6) -> 4225.2371 | Q7: =P7*(1+Q6) -> 4436.4989
B9: COGS % of Revenue | F9: -0.53333333 | G9: -0.50531915 | H9: -0.49582173 | I9: -0.54125413 | J9: -0.55660377 | K9: -0.55813953 | L9: ='DCF Inputs'!G14 -> 0.555 | M9: ='DCF Inputs'!H14 -> 0.553 | N9: ='DCF Inputs'!I14 -> 0.55 | O9: ='DCF Inputs'!J14 -> 0.548 | P9: ='DCF Inputs'!K14 -> 0.545 | Q9: ='DCF Inputs'!L14 -> 0.5225
B10: COGS | F10: 1520 | G10: 1900 | H10: 1780 | I10: 1640 | J10: 1770 | K10: 1920 | L10: =L7*L9 -> 2004.66 | M10: =M7*M9 -> 2077.3334 | N10: =N7*N9 -> 2138.3762 | O10: =O7*O9 -> 2205.1713 | P10: =P7*P9 -> 2302.7542 | Q10: =Q7*Q9 -> 2318.0707
B12: Income Statements
B14: All figures in USD mm unless stated | F14: 2020 | G14: =F14+1 -> 2021 | H14: =G14+1 -> 2022 | I14: =H14+1 -> 2023 | J14: =I14+1 -> 2024 | K14: =J14+1 -> 2025 | L14: =K14+1 -> 2026 | M14: =L14+1 -> 2027 | N14: =M14+1 -> 2028 | ... P14: =O14+1 -> 2030 | Q14: Terms
B16: Inflation | F16: 0.03 | G16: 0.03 | H16: 0.03 | I16: 0.03 | J16: 0.03 | K16: 0.03 | L16: ='DCF Inputs'!G26 -> 0.027 | M16: ='DCF Inputs'!H26 -> 0.025 | N16: ='DCF Inputs'!I26 -> 0.02 | O16: ='DCF Inputs'!J26 -> 0.02 | P16: ='DCF Inputs'!K26 -> 0.02 | Q16: ='DCF Inputs'!L26 -> 0.015
B18: Interest Expense | C18: ='DCF Inputs'!G41 -> 200
B19: Tax Rate | C19: ='DCF Inputs'!G47 -> 0.24
B21: Revenue | F21: 2850 | G21: 3760 | H21: 3590 | I21: 3030 | J21: 3180 | K21: 3440 | L21: =L7 -> 3612 | M21: =M7 -> 3756.48 | N21: =N7 -> 3887.9568 | O21: =O7 -> 4024.0353 | P21: =P7 -> 4225.2371 | Q21: =Q7 -> 4436.4989
B22: COGS | F22: -1355.83 | G22: -1731.5 | H22: -1596.23 | I22: -1521.01 | J22: -1639.81 | K22: -1771.5 | L22: =L10*-1-L29 -> -1805.9506 | M22: =M10*-1-M29 -> -1867.788 | N22: =N10*-1-N29 -> -1917.9948 | O22: =O10*-1-O29 -> -1973.9539 | P22: =P10*-1-P29 -> -2060.7008 | Q22: =Q10*-1-Q29 -> -2109.5552
B23: Gross Profit | F23: 1330 | G23: 1860 | H23: 1810 | I23: 1390 | J23: 1410 | K23: 1520 | L23: =SUM(L21:L22) -> 1806.0494 | M23: =SUM(M21:M22) -> 1888.692 | N23: =SUM(N21:N22) -> 1969.962 | O23: =SUM(O21:O22) -> 2050.0814 | P23: =SUM(P21:P22) -> 2164.5363 | Q23: =SUM(Q21:Q22) -> 2326.9437
B25: SG&A | F25: -839.52 | G25: -922 | H25: -1070 | I25: -1030 | J25: -1050 | K25: -1130 | L25: =K25*(1+L16) -> -1160.51 | M25: =L25*(1+M16) -> -1189.5227 | N25: =M25*(1+N16) -> -1213.3132 | O25: =N25*(1+O16) -> -1237.5795 | P25: =O25*(1+P16) -> -1262.3311 | Q25: =P25*(1+Q16) -> -1281.266
B26: Other | F26: =F23-F27+F25 -> -162.11 | G26: =G23-G27+G25 -> -163 | H26: =H23-H27+H25 -> -189.85 | I26: =I23-I27+I25 -> -122.17 | J26: =J23-J27+J25 -> -137.95 | K26: =K23-K27+K25 -> -146.69 | L26: =K26*(1+L16) -> -150.65063 | M26: =L26*(1+M16) -> -154.4169 | N26: =M26*(1+N16) -> -157.50523 | O26: =N26*(1+O16) -> -160.65534 | P26: =O26*(1+P16) -> -163.86845 | Q26: =P26*(1+Q16) -> -166.32647
B27: EBITDA | F27: 652.59 | G27: 1101 | H27: 929.85 | I27: 482.17 | J27: 497.95 | K27: 536.69 | L27: =L23+L25+L26 -> 494.88877 | M27: =M23+M25+M26 -> 544.75231 | N27: =N23+N25+N26 -> 599.14352 | O27: =O23+O25+O26 -> 651.84654 | P27: =P23+P25+P26 -> 738.33676 | Q27: =Q23+Q25+Q26 -> 879.35118
B29: Depreciation | F29: -164.17 | G29: -168.5 | H29: -183.77 | I29: -118.99 | J29: -130.19 | K29: -148.5 | L29: =-L112 -> -198.7094 | M29: =-M112 -> -209.5454 | N29: =-N112 -> -220.3814 | O29: =-O112 -> -231.2174 | P29: =-P112 -> -242.0534 | Q29: =Q83*-1 -> -208.51545
B30: EBIT | F30: 488.41 | G30: 933.08 | H30: 746.08 | I30: 363.18 | J30: 367.75 | K30: 388.19 | L30: =L27+L29 -> 296.17937 | M30: =M27+M29 -> 335.20691 | N30: =N27+N29 -> 378.76212 | O30: =O27+O29 -> 420.62914 | P30: =P27+P29 -> 496.28336 | Q30: =Q27+Q29 -> 670.83573
B32: Interest | F32: -111.11 | G32: -102.76 | H32: -306.74 | I32: -196.48 | J32: -279.16 | K32: -221.25 | L32: =$C$18*-1 -> -200 | M32: =$C$18*-1 -> -200 | N32: =$C$18*-1 -> -200 | O32: =$C$18*-1 -> -200 | P32: =$C$18*-1 -> -200 | Q32: =$C$18*-1 -> -200
B33: EBT | F33: 377.3 | G33: 830.32 | H33: 439.34 | I33: 166.7 | J33: 88.59 | K33: 166.94 | L33: =SUM(L30:L32) -> 96.17937 | M33: =SUM(M30:M32) -> 135.20691 | N33: =SUM(N30:N32) -> 178.76212 | O33: =SUM(O30:O32) -> 220.62914 | P33: =SUM(P30:P32) -> 296.28336 | Q33: =SUM(Q30:Q32) -> 470.83573
B35: Current Tax | F35: -109.52 | G35: -140.48 | H35: -1.25 | I35: -2.96 | J35: -6.23 | K35: -21.59 | L35: =L165 -> 42.848921 | M35: =M165 -> 59.95778 | N35: =N165 -> 70.109385 | O35: =O165 -> 80.201279 | P35: =P165 -> 98.68869 | Q35: =Q33*C19 -> 113.00058
B36: Deferred Tax | F36: 4.92 | G36: 6.92 | H36: 92.61 | I36: -25.3 | J36: 1.43 | K36: -25.57 | L36: =L166 -> -19.765872 | M36: =M166 -> -27.50812 | N36: =N166 -> -27.206476 | O36: =O166 -> -27.250284 | P36: =P166 -> -27.580685 | Q36: =Q166 -> 0
B37: Total Tax | F37: 104.6 | G37: 133.56 | H37: 91.36 | I37: 28.26 | J37: 4.8 | K37: 47.16 | L37: =L167 -> 23.083049 | M37: =M167 -> 32.449659 | N37: =N167 -> 42.902909 | O37: =O167 -> 52.950994 | P37: =P167 -> 71.108005 | Q37: =SUM(Q35:Q36) -> 113.00058
B39: Net Income | F39: 271.81 | G39: 688.55 | H39: 528.64 | I39: 127.56 | J39: 72.41 | K39: 124.79 | L39: =L33-L37 -> 73.096321 | M39: =M33-M37 -> 102.75725 | N39: =N33-N37 -> 135.85921 | O39: =O33-O37 -> 167.67815 | P39: =P33-P37 -> 225.17535 | Q39: =Q33-Q37 -> 357.83516
B41: Working Capital Schedules
F43: 2020 | G43: =F43+1 -> 2021 | H43: =G43+1 -> 2022 | I43: =H43+1 -> 2023 | J43: =I43+1 -> 2024 | K43: =J43+1 -> 2025 | L43: =K43+1 -> 2026 | M43: =L43+1 -> 2027 | N43: =M43+1 -> 2028 | ... P43: =O43+1 -> 2030 | Q43: Terms
B45: Days in Period | F45: 365 | G45: 365 | H45: 365 | I45: 365 | J45: 365 | K45: 365 | L45: 365 | M45: 365 | N45: 365 | O45: 365 | P45: 365 | Q45: 365
B46: Revenue | F46: =F7 -> 2850 | G46: =G7 -> 3760 | H46: =H7 -> 3590 | I46: =I7 -> 3030 | J46: =J7 -> 3180 | K46: =K7 -> 3440 | L46: =L7 -> 3612 | M46: =M7 -> 3756.48 | ... Q46: =Q7 -> 4436.4989
B47: COGS | F47: =F10 -> 1520 | G47: =G10 -> 1900 | H47: =H10 -> 1780 | I47: =I10 -> 1640 | J47: =J10 -> 1770 | K47: =K10 -> 1920 | L47: =L10 -> 2004.66 | M47: =M10 -> 2077.3334 | ... Q47: =Q10 -> 2318.0707
B48: SG&A | F48: =F25*-1 -> 839.52 | G48: =G25*-1 -> 922 | H48: =H25*-1 -> 1070 | I48: =I25*-1 -> 1030 | J48: =J25*-1 -> 1050 | K48: =K25*-1 -> 1130 | L48: =L25*-1 -> 1160.51 | M48: =M25*-1 -> 1189.5227 | ... Q48: =Q25*-1 -> 1281.266
B49: prepaids % SG&A | F49: =F63/F25*-1 -> 0 | G49: =G63/G25*-1 -> 0 | H49: =H63/H25*(-1) -> 0.022757009 | I49: =I63/I25*(-1) -> 0.040864078 | J49: =J63/J25*(-1) -> 0.028180952 | K49: =K63/K25*(-1) -> 0.026867257 | L49: ='DCF Inputs'!G32 -> 0.025 | M49: ='DCF Inputs'!H32 -> 0.025 | N49: ='DCF Inputs'!I32 -> 0.025 | O49: ='DCF Inputs'!J32 -> 0.025 | P49: ='DCF Inputs'!K32 -> 0.025 | Q49: ='DCF Inputs'!L32 -> 0.025
B50: other operating Assets & Revenue | F50: =F64/F46 -> 0.017378947 | G50: =G64/G46 -> 0.013779255 | H50: =H64/H46 -> 0.0086991643 | I50: =I64/I46 -> 0.011267327 | J50: =J64/J46 -> 0.014688679 | K50: =K64/K46 -> 0.013697674 | L50: ='DCF Inputs'!G33 -> 0.012 | M50: ='DCF Inputs'!H33 -> 0.012 | N50: ='DCF Inputs'!I33 -> 0.012 | O50: ='DCF Inputs'!J33 -> 0.012 | P50: ='DCF Inputs'!K33 -> 0.012 | Q50: ='DCF Inputs'!L33 -> 0.012
B51: Accrued Payroll % SG&A | F51: =F66/F46 -> 0.029775439 | G51: =G66/G46 -> 0.025760638 | H51: =H66/H46 -> 0.021350975 | I51: =I66/I46 -> 0.014468647 | J51: =J66/J46 -> 0.015940252 | K51: =K66/K46 -> 0.015968023 | L51: ='DCF Inputs'!G34 -> 0.02 | M51: ='DCF Inputs'!H34 -> 0.02 | N51: ='DCF Inputs'!I34 -> 0.02 | O51: ='DCF Inputs'!J34 -> 0.02 | P51: ='DCF Inputs'!K34 -> 0.02 | Q51: ='DCF Inputs'!L34 -> 0.02
B52: Deferred Revenue (Current) % Revenue | F52: =F67/F46 -> 0.098470175 | G52: =G67/G46 -> 0.10317287 | H52: =H67/H46 -> 0.090738162 | I52: =I67/I46 -> 0.093336634 | J52: =J67/J46 -> 0.091764151 | K52: =K67/K46 -> 0.10367442 | L52: ='DCF Inputs'!G35 -> 0.1 | M52: ='DCF Inputs'!H35 -> 0.1 | N52: ='DCF Inputs'!I35 -> 0.1 | O52: ='DCF Inputs'!J35 -> 0.1 | P52: ='DCF Inputs'!K35 -> 0.1 | Q52: ='DCF Inputs'!L35 -> 0.1
B53: Other Current Liabilities & Revenue | F53: =F68/F46 -> 0.060610526 | G53: =G68/G46 -> 0.045109043 | H53: =H68/H46 -> 0.053548747 | I53: =I68/I46 -> 0.059745875 | J53: =J68/J46 -> 0.05190566 | K53: =K68/K46 -> 0.047052326 | L53: ='DCF Inputs'!G36 -> 0.05 | M53: ='DCF Inputs'!H36 -> 0.05 | N53: ='DCF Inputs'!I36 -> 0.05 | O53: ='DCF Inputs'!J36 -> 0.05 | P53: ='DCF Inputs'!K36 -> 0.05 | Q53: ='DCF Inputs'!L36 -> 0.05
B55: AMOUNTS PER DAY
B56: Accounts Receivable | D56: (Days) | F56: =F61/F46*F45 -> 9.3542456 | G56: =G61/G46*G45 -> 7.9280718 | H56: =H61/H46*H45 -> 9.7350279 | I56: =I61/I46*I45 -> 11.275248 | J56: =J61/J46*J45 -> 13.133113 | K56: =K61/K46*K45 -> 12.832297 | L56: ='DCF Inputs'!G29 -> 10 | M56: ='DCF Inputs'!H29 -> 10 | N56: ='DCF Inputs'!I29 -> 10 | O56: ='DCF Inputs'!J29 -> 10 | P56: ='DCF Inputs'!K29 -> 10 | Q56: ='DCF Inputs'!L29 -> 10
B57: Inventory | D57: (Days) | F57: =F62/F47*F45 -> 133.69326 | G57: =G62/G47*G45 -> 144.82816 | H57: =H62/H47*H45 -> 168.76944 | I57: =I62/I47*I45 -> 173.71552 | J57: =J62/J47*J45 -> 214.46328 | K57: =K62/K47*K45 -> 160.5962 | L57: ='DCF Inputs'!G30 -> 150 | M57: ='DCF Inputs'!H30 -> 150 | N57: ='DCF Inputs'!I30 -> 150 | O57: ='DCF Inputs'!J30 -> 150 | P57: ='DCF Inputs'!K30 -> 150 | Q57: ='DCF Inputs'!L30 -> 150
B58: Accounts Payable | D58: (Days) | F58: =F65/F47*F45 -> 54.007993 | G58: =G65/G47*G45 -> 46.495237 | H58: =H65/H47*H45 -> 34.05573 | I58: =I65/I47*I45 -> 42.807378 | J58: =J65/J47*J45 -> 50.576215 | K58: =K65/K47*K45 -> 37.591198 | L58: ='DCF Inputs'!G31 -> 45 | M58: ='DCF Inputs'!H31 -> 45 | N58: ='DCF Inputs'!I31 -> 45 | O58: ='DCF Inputs'!J31 -> 45 | P58: ='DCF Inputs'!K31 -> 45 | Q58: ='DCF Inputs'!L31 -> 45
B60: TOTAL AMOUNTS
B61: Accounts Receivable | F61: ='RH Financial Report'!C21 -> 73.04 | G61: ='RH Financial Report'!D21 -> 81.67 | H61: ='RH Financial Report'!E21 -> 95.75 | I61: ='RH Financial Report'!F21 -> 93.6 | J61: ='RH Financial Report'!G21 -> 114.42 | K61: ='RH Financial Report'!H21 -> 120.94 | L61: =L56/L45*L46 -> 98.958904 | M61: =M56/M45*M46 -> 102.91726 | N61: =N56/N45*N46 -> 106.51936 | O61: =O56/O45*O46 -> 110.24754 | P61: =P56/P45*P46 -> 115.75992 | Q61: =Q56/Q45*Q46 -> 121.54792
B62: Inventory | F62: ='RH Financial Report'!C22 -> 556.75 | G62: ='RH Financial Report'!D22 -> 753.9 | H62: ='RH Financial Report'!E22 -> 823.04 | I62: ='RH Financial Report'!F22 -> 780.53 | J62: ='RH Financial Report'!G22 -> 1040 | K62: ='RH Financial Report'!H22 -> 844.78 | L62: =L57/L45*L47 -> 823.83288 | M62: =M57/M45*M47 -> 853.69867 | N62: =N57/N45*N47 -> 878.78476 | O62: =O57/O45*O47 -> 906.2348 | P62: =P57/P45*P47 -> 946.33734 | Q62: =Q57/Q45*Q47 -> 952.63179
B63: prepaids | F63: ='RH Financial Report'!C24 -> 0 | G63: ='RH Financial Report'!D24 -> 0 | H63: ='RH Financial Report'!E24 -> 24.35 | I63: ='RH Financial Report'!F24 -> 42.09 | J63: ='RH Financial Report'!G24 -> 29.59 | K63: ='RH Financial Report'!H24 -> 30.36 | L63: =L49*L48 -> 29.01275 | M63: =M49*M48 -> 29.738069 | N63: =N49*N48 -> 30.33283 | O63: =O49*O48 -> 30.939487 | P63: =P49*P48 -> 31.558276 | Q63: =Q49*Q48 -> 32.031651
B64: other operating Assets | F64: ='RH Financial Report'!C23 -> 49.53 | G64: ='RH Financial Report'!D23 -> 51.81 | H64: ='RH Financial Report'!E23 -> 31.23 | I64: ='RH Financial Report'!F23 -> 34.14 | J64: ='RH Financial Report'!G23 -> 46.71 | K64: ='RH Financial Report'!H23 -> 47.12 | L64: =L50*L46 -> 43.344 | M64: =M50*M46 -> 45.07776 | N64: =N50*N46 -> 46.655482 | O64: =O50*O46 -> 48.288423 | P64: =P50*P46 -> 50.702845 | Q64: =Q50*Q46 -> 53.237987
B65: Accounts Payable | F65: ='RH Financial Report'!C33 -> 224.91 | G65: ='RH Financial Report'!D33 -> 242.03 | H65: ='RH Financial Report'!E33 -> 166.08 | I65: ='RH Financial Report'!F33 -> 192.34 | J65: ='RH Financial Report'!G33 -> 245.26 | K65: ='RH Financial Report'!H33 -> 197.74 | L65: =L58/L45*L47 -> 247.14986 | M65: =M58/M45*M47 -> 256.1096 | N65: =N58/N45*N47 -> 263.63543 | O65: =O58/O45*O47 -> 271.87044 | P65: =P58/P45*P47 -> 283.9012 | Q65: =Q58/Q45*Q47 -> 285.78954
B66: Accrued Payroll | F66: ='RH Financial Report'!C34 -> 84.86 | G66: ='RH Financial Report'!D34 -> 96.86 | H66: ='RH Financial Report'!E34 -> 76.65 | I66: ='RH Financial Report'!F34 -> 43.84 | J66: ='RH Financial Report'!G34 -> 50.69 | K66: ='RH Financial Report'!H34 -> 54.93 | L66: =L51*L47 -> 40.0932 | M66: =M51*M47 -> 41.546669 | N66: =N51*N47 -> 42.767525 | O66: =O51*O47 -> 44.103427 | P66: =P51*P47 -> 46.055084 | Q66: =Q51*Q47 -> 46.361414
B67: Deferred Revenue (Current) | F67: ='RH Financial Report'!C35 -> 280.64 | G67: ='RH Financial Report'!D35 -> 387.93 | H67: ='RH Financial Report'!E35 -> 325.75 | I67: ='RH Financial Report'!F35 -> 282.81 | J67: ='RH Financial Report'!G35 -> 291.81 | K67: ='RH Financial Report'!H35 -> 356.64 | L67: =L52*L46 -> 361.2 | M67: =M52*M46 -> 375.648 | N67: =N52*N46 -> 388.79568 | O67: =O52*O46 -> 402.40353 | P67: =P52*P46 -> 422.52371 | Q67: =Q52*Q46 -> 443.64989
B68: Other Current Liabilities | F68: ='RH Financial Report'!C36 -> 172.74 | G68: ='RH Financial Report'!D36 -> 169.61 | H68: ='RH Financial Report'!E36 -> 192.24 | I68: ='RH Financial Report'!F36 -> 181.03 | J68: ='RH Financial Report'!G36 -> 165.06 | K68: ='RH Financial Report'!H36 -> 161.86 | L68: =L53*L46 -> 180.6 | M68: =M53*M46 -> 187.824 | N68: =N53*N46 -> 194.39784 | O68: =O53*O46 -> 201.20176 | P68: =P53*P46 -> 211.26185 | Q68: =Q53*Q46 -> 221.82495
B70: NET WORKING CAPITAL
B71: Current Assets | F71: =SUM(F61:F64) -> 679.32 | G71: =SUM(G61:G64) -> 887.38 | H71: =SUM(H61:H64) -> 974.37 | I71: =SUM(I61:I64) -> 950.36 | J71: =SUM(J61:J64) -> 1230.72 | K71: =SUM(K61:K64) -> 1043.2 | L71: =SUM(L61:L64) -> 995.14853 | M71: =SUM(M61:M64) -> 1031.4318 | ... Q71: =SUM(Q61:Q64) -> 1159.4493
B72: Current Liabilities | F72: =SUM(F65:F68) -> 763.15 | G72: =SUM(G65:G68) -> 896.43 | H72: =SUM(H65:H68) -> 760.72 | I72: =SUM(I65:I68) -> 700.02 | J72: =SUM(J65:J68) -> 752.82 | K72: =SUM(K65:K68) -> 771.17 | L72: =SUM(L65:L68) -> 829.04306 | M72: =SUM(M65:M68) -> 861.12827 | ... Q72: =SUM(Q65:Q68) -> 997.62578
B73: Net Working Capital | F73: =F71-F72 -> -83.83 | G73: =G71-G72 -> -9.05 | H73: =H71-H72 -> 213.65 | I73: =I71-I72 -> 250.34 | J73: =J71-J72 -> 477.9 | K73: =K71-K72 -> 272.03 | L73: =L71-L72 -> 166.10547 | M73: =M71-M72 -> 170.30349 | ... Q73: =Q71-Q72 -> 161.82355
B76: Cash from Working Capital Items | G76: =F73-G73 -> -74.78 | H76: =G73-H73 -> -222.7 | I76: =H73-I73 -> -36.69 | J76: =I73-J73 -> -227.56 | K76: =J73-K73 -> 205.87 | L76: =K73-L73 -> 105.92453 | M76: =L73-M73 -> -4.1980242 | N76: =M73-N73 -> -2.3924686 | ... Q76: =P73-Q73 -> 18.792983
B78: Deperiation Schedules
B80: All figures in USD mm unless stated | F80: 2020 | G80: =F80+1 -> 2021 | H80: =G80+1 -> 2022 | I80: =H80+1 -> 2023 | J80: =I80+1 -> 2024 | K80: =J80+1 -> 2025 | L80: =K80+1 -> 2026 | M80: =L80+1 -> 2027 | N80: =M80+1 -> 2028 | ... P80: =O80+1 -> 2030 | Q80: Term
B82: CapEx % of Revenue | F82: =F83/F7 -> 0.038992982 | G82: =G83/G7 -> 0.049303191 | H82: =H83/H7 -> 0.048367688 | I82: =I83/I7 -> 0.08889769 | J82: =J83/J7 -> 0.072575472 | K82: =K83/K7 -> 0.058994186 | L82: ='DCF Inputs'!G20 -> 0.06 | M82: ='DCF Inputs'!H20 -> 0.058 | N82: ='DCF Inputs'!I20 -> 0.055 | O82: ='DCF Inputs'!J20 -> 0.053 | P82: ='DCF Inputs'!K20 -> 0.05 | Q82: ='DCF Inputs'!L20 -> 0.047
B83: Capital Expenditure | F83: ='RH Financial Report'!C57*-1 -> 111.13 | G83: ='RH Financial Report'!D57*-1 -> 185.38 | H83: ='RH Financial Report'!E57*-1 -> 173.64 | I83: ='RH Financial Report'!F57*-1 -> 269.36 | J83: ='RH Financial Report'!G57*-1 -> 230.79 | K83: ='RH Financial Report'!H57*-1 -> 202.94 | L83: =L7*L82 -> 216.72 | M83: =M7*M82 -> 217.87584 | N83: =N7*N82 -> 213.83762 | O83: =O7*O82 -> 213.27387 | P83: =P7*P82 -> 211.26185 | Q83: =Q7*Q82 -> 208.51545
B85: EXISTING ASSET DEPRECIATION | D85: Years | L85: Percent of Full Year
B86: Useful Life: Existing Assets | D86: ='DCF Inputs'!G45 -> 16 | L86: 1 | M86: =L86+1 -> 2 | N86: =M86+1 -> 3 | O86: =N86+1 -> 4 | P86: =O86+1 -> 5
B87: =CONCATENATE("PP&E at End of ",K80) -> PP&E at End of 2025 | D87: ='RH Financial Report'!H27 -> 3110 | L87: =MIN($D86-SUM($K87:K87),1) -> 1 | M87: =MIN($D86-SUM($K87:L87),1) -> 1 | N87: =MIN($D86-SUM($K87:M87),1) -> 1 | O87: =MIN($D86-SUM($K87:N87),1) -> 1 | P87: =MIN($D86-SUM($K87:O87),1) -> 1
B89: NEW ASSET DEPRECIATION | D89: Years | L89: Percent of Full Year
B90: Useful Life: New Assets | D90: ='DCF Inputs'!G46 -> 20 | L90: 1 | M90: =L90+1 -> 2 | N90: =M90+1 -> 3 | O90: =N90+1 -> 4 | P90: =O90+1 -> 5
B91: First Year Accounting Depreciation | D91: ='DCF Inputs'!G44 -> 0.4 | L91: =IF(K91="",D91,MIN($D90-SUM($D91:D91),1)) -> 0.4 | M91: =IF(L91="",E91,MIN($D90-SUM($D91:E91),1)) -> 1 | N91: =IF(M91="",F91,MIN($D90-SUM($D91:F91),1)) -> 1 | O91: =IF(N91="",G91,MIN($D90-SUM($D91:G91),1)) -> 1 | P91: =IF(O91="",H91,MIN($D90-SUM($D91:H91),1)) -> 1
I94: Year | J94: Life | L94: =L80 -> 2026 | M94: =M80 -> 2027 | N94: =N80 -> 2028 | O94: =O80 -> 2029 | P94: =P80 -> 2030
I95: =L80 -> 2026 | J95: =$D$90 -> 20 | L95: =L91 -> 0.4 | M95: =M91 -> 1 | N95: =N91 -> 1 | O95: =O91 -> 1 | P95: =P91 -> 1
I96: =I95+1 -> 2027 | J96: =$D$90 -> 20 | L96: =K95 -> 0 | M96: =L95 -> 0.4 | N96: =M95 -> 1 | O96: =N95 -> 1 | P96: =O95 -> 1
I97: =I96+1 -> 2028 | J97: =$D$90 -> 20 | L97: =K96 -> 0 | M97: =L96 -> 0 | N97: =M96 -> 0.4 | O97: =N96 -> 1 | P97: =O96 -> 1
I98: =I97+1 -> 2029 | J98: =$D$90 -> 20 | L98: =K97 -> 0 | M98: =L97 -> 0 | N98: =M97 -> 0 | O98: =N97 -> 0.4 | P98: =O97 -> 1
I99: =I98+1 -> 2030 | J99: =$D$90 -> 20 | L99: =K98 -> 0 | M99: =L98 -> 0 | N99: =M98 -> 0 | O99: =N98 -> 0 | P99: =O98 -> 0.4
L101: Amounts for Depreciation
I102: Year | J102: Capex | K102: Per Yr | L102: =L94 -> 2026 | M102: =M94 -> 2027 | N102: =N94 -> 2028 | O102: =O94 -> 2029 | P102: =P94 -> 2030
I103: =I95 -> 2026 | J103: =SUMIF($L$80:$P$80,I103,$L$83:$P$83) -> 216.72 | K103: =J103/J95 -> 10.836 | L103: =L95*$K$103 -> 4.3344 | M103: =M95*$K$103 -> 10.836 | N103: =N95*$K$103 -> 10.836 | O103: =O95*$K$103 -> 10.836 | P103: =P95*$K$103 -> 10.836
I104: =I96 -> 2027 | J104: =SUMIF($L$80:$P$80,I104,$L$83:$P$83) -> 217.87584 | K104: =J104/J96 -> 10.893792 | L104: =L96*$K$103 -> 0 | M104: =M96*$K$103 -> 4.3344 | N104: =N96*$K$103 -> 10.836 | O104: =O96*$K$103 -> 10.836 | P104: =P96*$K$103 -> 10.836
I105: =I97 -> 2028 | J105: =SUMIF($L$80:$P$80,I105,$L$83:$P$83) -> 213.83762 | K105: =J105/J97 -> 10.691881 | L105: =L97*$K$103 -> 0 | M105: =M97*$K$103 -> 0 | N105: =N97*$K$103 -> 4.3344 | O105: =O97*$K$103 -> 10.836 | P105: =P97*$K$103 -> 10.836
I106: =I98 -> 2029 | J106: =SUMIF($L$80:$P$80,I106,$L$83:$P$83) -> 213.27387 | K106: =J106/J98 -> 10.663694 | L106: =L98*$K$103 -> 0 | M106: =M98*$K$103 -> 0 | N106: =N98*$K$103 -> 0 | O106: =O98*$K$103 -> 4.3344 | P106: =P98*$K$103 -> 10.836
I107: =I99 -> 2030 | J107: =SUMIF($L$80:$P$80,I107,$L$83:$P$83) -> 211.26185 | K107: =J107/J99 -> 10.563093 | L107: =L99*$K$103 -> 0 | M107: =M99*$K$103 -> 0 | N107: =N99*$K$103 -> 0 | O107: =O99*$K$103 -> 0 | P107: =P99*$K$103 -> 4.3344
E109: TOTAL ASSET DEPRECIATION
E110: Existing Assets | L110: =$D$87/$D$86*L87 -> 194.375 | M110: =$D$87/$D$86*M87 -> 194.375 | N110: =$D$87/$D$86*N87 -> 194.375 | O110: =$D$87/$D$86*O87 -> 194.375 | P110: =$D$87/$D$86*P87 -> 194.375
E111: New Assets | L111: =SUM(L103:L107) -> 4.3344 | M111: =SUM(M103:M107) -> 15.1704 | N111: =SUM(N103:N107) -> 26.0064 | O111: =SUM(O103:O107) -> 36.8424 | P111: =SUM(P103:P107) -> 47.6784
E112: Total Depreciation | L112: =SUM(L110:L111) -> 198.7094 | M112: =SUM(M110:M111) -> 209.5454 | N112: =SUM(N110:N111) -> 220.3814 | O112: =SUM(O110:O111) -> 231.2174 | P112: =SUM(P110:P111) -> 242.0534
B114: Assets Schedules
B116: All figures in USD mm unless stated | L116: 2026 | M116: =L116+1 -> 2027 | N116: =M116+1 -> 2028 | O116: =N116+1 -> 2029 | P116: =O116+1 -> 2030
B119: Capital Expenditure | L119: =L83 -> 216.72 | M119: =M83 -> 217.87584 | N119: =N83 -> 213.83762 | O119: =O83 -> 213.27387 | P119: =P83 -> 211.26185
B121: First Year Tax Depreciation | D121: ='DCF Inputs'!G42 -> 0.5
B122: Blended Tax Depreciation Rate | D122: ='DCF Inputs'!G43 -> 0.1
B124: PROPERTY PLANT & EQUIPMENT 1
B125: Beginning | L125: =K128 -> 3110 | M125: =L128 -> 3128.0106 | N125: =M128 -> 3136.341 | O125: =N128 -> 3129.7973 | P125: =O128 -> 3111.8537
B126: Capital Expenditure | L126: =L119 -> 216.72 | M126: =M119 -> 217.87584 | N126: =N119 -> 213.83762 | O126: =O119 -> 213.27387 | P126: =P119 -> 211.26185
B127: Accounting Depreciation | L127: =L112*-1 -> -198.7094 | M127: =M112*-1 -> -209.5454 | N127: =N112*-1 -> -220.3814 | O127: =O112*-1 -> -231.2174 | P127: =P112*-1 -> -242.0534
B128: Ending | K128: =D87 -> 3110 | L128: =SUM(L125:L127) -> 3128.0106 | M128: =SUM(M125:M127) -> 3136.341 | N128: =SUM(N125:N127) -> 3129.7973 | O128: =SUM(O125:O127) -> 3111.8537 | P128: =SUM(P125:P127) -> 3081.0622
B130: TAX BASIS 1
B131: Beginning | L131: =K134 -> 704.956 | M131: =L134 -> 840.3444 | N131: =M134 -> 963.29201 | O131: =N134 -> 1070.1086 | P131: =O134 -> 1165.7079
B132: Capital Expenditure | L132: =L126 -> 216.72 | M132: =M126 -> 217.87584 | N132: =N126 -> 213.83762 | O132: =O126 -> 213.27387 | P132: =P126 -> 211.26185
B133: Tax Depreciation | L133: =(L131+L132*$D$121)*$D$122*-1 -> -81.3316 | M133: =(M131+M132*$D$121)*$D$122*-1 -> -94.928232 | N133: =(N131+N132*$D$121)*$D$122*-1 -> -107.02108 | O133: =(O131+O132*$D$121)*$D$122*-1 -> -117.67455 | P133: =(P131+P132*$D$121)*$D$122*-1 -> -127.13388
B134: Ending | K134: ='DCF Inputs'!M43 -> 704.956 | L134: =SUM(L131:L133) -> 840.3444 | M134: =SUM(M131:M133) -> 963.29201 | N134: =SUM(N131:N133) -> 1070.1086 | O134: =SUM(O131:O133) -> 1165.7079 | P134: =SUM(P131:P133) -> 1249.8358
B136: Income Tax Schedule (levered)
L137: 2026 | M137: =L137+1 -> 2027 | N137: =M137+1 -> 2028 | O137: =N137+1 -> 2029 | P137: =O137+1 -> 2030
B138: All figures in USD mm unless stated
L139: =L33 -> 96.17937 | M139: =M33 -> 135.20691 | N139: =N33 -> 178.76212 | O139: =O33 -> 220.62914 | P139: =P33 -> 296.28336
...

Sheet Comps
B2: Comparable Trading Analysis
B4: All figures in USD mm unless stated
D6: Share | E6: Enterprise | G6: EV /
B7: Peer Companies | C7: Ticker | D7: Price | E7: Value | F7: EBITDA | G7: EBITDA | H7: EBITDA Growth | J7: EPS | K7: P / E
D9: (USD/sh) | F9: (LTM) | G9: (LTM) | H9: (FY+1) | I9: (FY+2) | J9: (LTM) | K9: (LTM)
B10: Arhaus | C10: ARHS | D10: 14.63 | E10: 160.59 | F10: 15.91 | G10: =E10/F10 -> 10.093652 | H10: 0.07 | I10: 0.05 | J10: 0.62 | K10: =D10/J10 -> 23.596774
B11: Ethan Allen Interiors | C11: ETD | D11: 23.7 | E11: 488.82 | F11: 46.44 | G11: =E11/F11 -> 10.52584 | H11: 0.06 | I11: 0.06 | J11: 1.31 | K11: =D11/J11 -> 18.091603
B12: Haverty Furniture | C12: HVT | D12: 20.57 | E12: 537.43 | F12: 59.81 | G12: =E12/F12 -> 8.9856211 | H12: 0.03 | I12: 0.04 | J12: 1.58 | K12: =D12/J12 -> 13.018987
B13: MillerKnoll | C13: MLKN | D13: 16.36 | E13: 2790 | F13: 362.3 | G13: =E13/F13 -> 7.7008004 | H13: 0.05 | I13: 0.062 | J13: 0.15 | K13: =D13/J13 -> 109.06667
B14: Hooker Furnishings | C14: HOFT | D14: 203.18 | E14: 24770 | F14: 1650 | G14: =E14/F14 -> 15.012121 | H14: 0.05 | I14: 0.02 | J14: 9.06 | K14: =D14/J14 -> 22.426049
B15: Leggett & Platt | C15: LEG | D15: 6.65 | E15: 1360 | F15: 178.08 | G15: =E15/F15 -> 7.6370171 | H15: 0.1 | I15: 0.08 | J15: 0.46 | K15: =D15/J15 -> 14.456522
B16: La-Z-Boy | C16: LZB | D16: 37.57 | E16: 1810 | F16: 263.08 | G16: =E16/F16 -> 6.8800365 | H16: 0.09 | I16: 0.098 | J16: 2.03 | K16: =D16/J16 -> 18.507389
B18: Target Company Valuation
B20: All figures in USD mm unless stated
E22: Enterprise | G22: EV / | J22: Equity
B23: Target Company Valuation 1, 2 | E23: Value | F23: EBITDA | G23: EBITDA | H23: EBITDA Growth | J23: Value
F25: (LTM) | G25: (LTM) | H25: (FY+1) | I25: (FY+2)
B26: Average | E26: =G26*F26 -> 5365.0866 | F26: 538 | G26: =AVERAGE($G$11:$G$15) -> 9.9722799 | H26: 0.07 | I26: 0.07 | J26: =(E26-'DCF Inputs'!$M$41)/'DCF Inputs'!$G$50 -> 79.727033
B27: Median | E27: =G27*F27 -> 4834.2642 | F27: =F26 -> 538 | G27: =MEDIAN($G$11:$G$15) -> 8.9856211 | H27: =H26 -> 0.07 | I27: =I26 -> 0.07 | J27: =(E27-'DCF Inputs'!$M$41)/'DCF Inputs'!$G$50 -> 50.236898
B28: Maximum | E28: =G28*F28 -> 8076.5212 | F28: =F27 -> 538 | G28: =MAX($G$11:$G$15) -> 15.012121 | H28: =H27 -> 0.07 | I28: =I27 -> 0.07 | J28: =(E28-'DCF Inputs'!$M$41)/'DCF Inputs'!$G$50 -> 230.36229
B29: Minimum | E29: =G29*F29 -> 4108.7152 | F29: =F28 -> 538 | G29: =MIN($G$11:$G$15) -> 7.6370171 | H29: =H28 -> 0.07 | I29: =I28 -> 0.07 | J29: =(E29-'DCF Inputs'!$M$41)/'DCF Inputs'!$G$50 -> 9.9286213
B31: =IF(SUM(E31:G31)=2,"COMPLETE","")
I33: Target company valuation based on LTM EV/EBITDA multiple.
I34: Summary results above exclude La-Z-Boy

Sheet Transactions
B2: Precedent Transaction Analysis
B4: All figures in USD mm unless stated
E6: Offer | F6: Premium | G6: Offer | H6: Transaction | J6: EV /
B7: Announcement Date | C7: Acquirer | D7: Target | E7: Price | F7: Paid | G7: Type | H7: Value | I7: EBITDA | J7: EBITDA | K7: EBITDA Growth | M7: EPS | N7: P / E
B9: (YYYY-MM-DD) | E9: (USD/sh) | I9: (LTM) | J9: (LTM) | K9: (FY+1) | L9: (FY+2) | M9: (LTM) | N9: (LTM)
B11: 2021-05-06 1 | C11: Hellman & Friedman | D11: At Home Group Inc. | E11: 36 | F11: 0.174 | G11: Cash | H11: 2800 | I11: 310.72 | J11: =H11/I11 -> 9.0113285 | K11: 0.09 | L11: 0.08 | M11: 4.56 | N11: =E11/M11 -> 7.8947368
B12: 2021-03-03 2 | C12: Apollo Global Management | D12: The Michaels Companies, Inc. | E12: 22 | F12: 0.467 | G12: Cash | H12: 5000 | I12: 693 | J12: =H12/I12 -> 7.2150072 | K12: 0.1 | L12: 0.09 | M12: 1.94 | N12: =E12/M12 -> 11.340206
B13: 2016-08-08 3 | C13: Steinhoff International Holdings N.V. | D13: Mattress Firm Holding Corp. | E13: 64 | F13: 1.152 | G13: Cash | H13: 3800 | I13: 222.6 | J13: =H13/I13 -> 17.070979 | K13: 0.12 | L13: 0.11 | M13: 4.52 | N13: =E13/M13 -> 14.159292
B14: 2023-03-08 6 | C14: HNI Corporation | D14: Kimball International, Inc. | E14: 12.9 | F14: 0.923 | G14: Mixed | H14: 485 | I14: 51.83 | J14: =H14/I14 -> 9.357515 | K14: 0.07 | L14: 0.07 | M14: 1.2 | N14: =E14/M14 -> 10.75
B15: 2016-02-03 8 | C15: Lowe’s Companies, Inc. | D15: RONA inc. | E15: 24 | F15: 1.039 | G15: Cash | H15: 3200 | I15: 428 | J15: =H15/I15 -> 7.4766355 | K15: 0.07 | L15: 0.07 | M15: 1.2 | N15: =E15/M15 -> 20
B18: Target Company Valuation
B20: All figures in USD mm unless stated
H22: Enterprise | J22: EV / | M22: Equity
B23: Target Company Valuation 1 | H23: Value | I23: EBITDA | J23: EBITDA | K23: EBITDA Growth | M23: Value
I25: (LTM) | J25: (LTM) | K25: (FY+1) | L25: (FY+2)
B26: Average | H26: =J26*I26 -> 5394.1457 | I26: 538 | J26: =AVERAGE($J$11:$J$15) -> 10.026293 | K26: 0.07 | L26: 0.07 | M26: =(H26-'DCF Inputs'!$M$41)/'DCF Inputs'!$G$50 -> 81.341427
B27: Median | H27: =J27*I27 -> 4848.0947 | I27: =I26 -> 538 | J27: =MEDIAN($J$11:$J$15) -> 9.0113285 | K27: =K26 -> 0.07 | L27: =L26 -> 0.07 | M27: =(H27-'DCF Inputs'!$M$41)/'DCF Inputs'!$G$50 -> 51.005264
B28: Maximum | H28: =J28*I28 -> 9184.1869 | I28: =I27 -> 538 | J28: =MAX($J$11:$J$15) -> 17.070979 | K28: =K27 -> 0.07 | L28: =L27 -> 0.07 | M28: =(H28-'DCF Inputs'!$M$41)/'DCF Inputs'!$G$50 -> 291.89927
B29: Minimum | H29: =J29*I29 -> 3881.6739 | I29: =I28 -> 538 | J29: =MIN($J$11:$J$15) -> 7.2150072 | K29: =K28 -> 0.07 | L29: =L28 -> 0.07 | M29: =(H29-'DCF Inputs'!$M$41)/'DCF Inputs'!$G$50 -> -2.6847844
B31: =IF(SUM(H31:J31)=2,"COMPLETE","")
L33: Target company valuation based on LTM EV/EBITDA multiple.

Sheet RH Financial Report
B2: Income Statements
B3: USD MM | C3: 2020 | D3: 2021 | E3: 2022 | F3: 2023 | G3: 2024 | H3: 2025
B4: Revenue | C4: 2850 | D4: 3760 | E4: 3590 | F4: 3030 | G4: 3180 | H4: 3440
B5: COGS with DA | C5: -1520 | D5: -1900 | E5: -1780 | F5: -1640 | G5: -1770 | H5: -1920
B6: COGS less DA | C6: =C5+C16 -> -1355.83 | D6: =D5+D16 -> -1731.5 | E6: =E5+E16 -> -1596.23 | F6: =F5+F16 -> -1521.01 | G6: =G5+G16 -> -1639.81 | H6: =H5+H16 -> -1771.5
B7: Gross Profit | C7: 1330 | D7: 1860 | E7: 1810 | F7: 1390 | G7: 1410 | H7: 1520
B8: Operating Expenses/SG&A | C8: -840 | D8: -922 | E8: -1070 | F8: -1030 | G8: -1050 | H8: -1130
B9: EBIT / Operating Income | C9: 488.41 | D9: 933.08 | E9: 746.08 | F9: 363.18 | G9: 367.75 | H9: 388.19
B10: EBITDA | C10: 652.59 | D10: 1101 | E10: 929.85 | F10: 482.17 | G10: 497.95 | H10: 536.69
B11: Pretax Income | C11: 377.3 | D11: 830.32 | E11: 439.34 | F11: 166.7 | G11: 88.59 | H11: 166.94
B12: Income Tax (Current) | C12: -109.52 | D12: -140.48 | E12: -1.25 | F12: -2.96 | G12: -6.23 | H12: -21.59
B13: Income Tax, Deferred | C13: 4.92 | D13: 6.92 | E13: 92.61 | F13: -25.3 | G13: 1.43 | H13: -25.57
B14: Taxes | C14: -104.6 | D14: -133.56 | E14: 91.36 | F14: -28.26 | G14: -4.8 | H14: -47.16
B15: Net Income | C15: 271.81 | D15: 688.55 | E15: 528.64 | F15: 127.56 | G15: 72.41 | H15: 124.79
B16: D&A | C16: 164.17 | D16: 168.5 | E16: 183.77 | F16: 118.99 | G16: 130.19 | H16: 148.5
B17: Balance Sheet
B18: USD MM | C18: 2020 | D18: 2021 | E18: 2022 | F18: 2023 | G18: 2024 | H18: 2025
B19: Current Assets
B20: Cash & Short-term Investments | C20: 103.1 | D20: 2180 | E20: 1510 | F20: 123.69 | G20: 30.41 | H20: 41.19
B21: Accounts Receivable | C21: 73.04 | D21: 81.67 | E21: 95.75 | F21: 93.6 | G21: 114.42 | H21: 120.94
B22: Inventory | C22: 556.75 | D22: 753.9 | E22: 823.04 | F22: 780.53 | G22: 1040 | H22: 844.78
B23: Other Current Assets | C23: 49.53 | D23: 51.81 | E23: 31.23 | F23: 34.14 | G23: 46.71 | H23: 47.12
B24: Prepaid Expense | C24: 0 | D24: 0 | E24: 24.35 | F24: 42.09 | G24: 29.59 | H24: 30.36
B25: Total Current Assets | C25: 782.42 | D25: 3070 | E25: 2490 | F25: 1070 | G25: 1260 | H25: 1080
B26: Long Term Assets
B27: Net PP&E | C27: 1670 | D27: 1980 | E27: 2210 | F27: 2430 | G27: 2640 | H27: 3110
B28: Long-term Investments | C28: 104.58 | D28: 100.81 | E28: 101.47 | F28: 128.67 | G28: 126.91 | H28: 119.75
B29: Intangible Assets | C29: 212.76 | D29: 214.26 | E29: 215.68 | F29: 216.96 | G29: 217.06 | H29: 224.02
B30: Total Assets | C30: 2900 | D30: 5540 | E30: 5310 | F30: 4140 | G30: 4550 | H30: 4840
B31: Current Liability
B32: Short-term Debt | C32: 108.94 | D32: 135.96 | E32: 125.25 | F32: 167.03 | G32: 147.08 | H32: 156.53
B33: Accounts Payable | C33: 224.91 | D33: 242.03 | E33: 166.08 | F33: 192.34 | G33: 245.26 | H33: 197.74
B34: Accrued Payroll | C34: 84.86 | D34: 96.86 | E34: 76.65 | F34: 43.84 | G34: 50.69 | H34: 54.93
B35: Deferred Revenue (Current) | C35: 280.64 | D35: 387.93 | E35: 325.75 | F35: 282.81 | G35: 291.81 | H35: 356.64
B36: Other Current Liabilities | C36: 172.74 | D36: 169.61 | E36: 192.24 | F36: 181.03 | G36: 165.06 | H36: 161.86
B37: Total Current Liabilities | C37: 921.63 | D37: 1060 | E37: 885.97 | F37: 872.87 | G37: 905.13 | H37: 930.61
B38: Long Term Liability
B39: Long-term Debt | C39: 1510 | D39: 3300 | E39: 3620 | F39: 3550 | G39: 3790 | H39: 3810
B40: Total Debt | C40: 1620 | D40: 3430 | E40: 3750 | F40: 3720 | G40: 3940 | H40: 3970
B41: Net Debt | C41: 1520 | D41: 1250 | E41: 2240 | F41: 3590 | G41: 3910 | H41: 3930
B42: Equity
B43: Shareholders’ Equity | C43: 447.03 | D43: 1170 | E43: 784.66 | F43: -297.39 | G43: -163.59 | H43: 60.6
B44: CashFlow Statements
B45: USD MM | C45: 2020 | D45: 2021 | E45: 2022 | F45: 2023 | G45: 2024 | H45: 2025
B46: Operating
B47: Cash from Operating Activities | C47: 500.77 | D47: 662.11 | E47: 403.69 | F47: 202.21 | G47: 17.09 | H47: 452.24
B48: Funds from Operations | C48: 607.55 | D48: 940.86 | E48: 902.09 | F48: 458.3 | G48: 431.64 | H48: 501.43
B49: Net Income | C49: 271.81 | D49: 688.55 | E49: 528.64 | F49: 127.56 | G49: 72.41 | H49: 124.79
B50: D&A | C50: 164.17 | D50: 168.5 | E50: 183.77 | F50: 118.99 | G50: 130.19 | H50: 148.5
B51: Current Taxes
B52: Deferred Taxes | C52: -4.92 | D52: -6.92 | E52: -91.99 | F52: 25.27 | G52: -1.49 | H52: 25.63
B53: Non-Cash Items | C53: 176.48 | D53: 90.74 | E53: 281.66 | F53: 186.48 | G53: 230.53 | H53: 202.51
B54: Change in Working Capital | C54: -106.78 | D54: -278.75 | E54: -498.4 | F54: -256.08 | G54: -414.55 | H54: -49.18
B55: Invetment/Financing
B56: Cash from Investing Activities | C56: -197.6 | D56: -194.35 | E56: -171.07 | F56: -307.43 | G56: -240.41 | H56: -223.69
B57: CapEx | C57: -111.13 | D57: -185.38 | E57: -173.64 | F57: -269.36 | G57: -230.79 | H57: -202.94
B58: Purchase/Sale of Investments | C58: -80.72 | D58: -8.97 | E58: -2.71 | F58: -38.08 | G58: -9.62 | H58: 9.29
B59: Cash from Financing Activities | C59: -243.91 | D59: 1610 | E59: -902.48 | F59: -1280 | G59: 130.59 | H59: -219.4
B60: Issuance/Retirement of Stock | C60: 14.38 | D60: 32.05 | E60: -768.7 | F60: -1240 | G60: 18.92 | H60: 4.39
B61: Issuance/Retirement of Debt | C61: -249.94 | D61: 1600 | E61: 266.02 | F61: -41.85 | G61: 112.22 | H61: -221.38
B62: Dividends Paid | C62: 0 | D62: 0 | E62: 0 | F62: 0 | G62: 0 | H62: 0
B63: Free Cash Flow | C63: 389.64 | D63: 476.73 | E63: 230.04 | F63: -67.14 | G63: -213.69 | H63: 252.4
B64: Working Capital Detail
B65: USD MM | C65: 2020 | D65: 2021 | E65: 2022 | F65: 2023 | G65: 2024 | H65: 2025
B66: Change in A/R | C66: -10.48 | D66: 1.56 | E66: -1.85 | F66: 4.69 | G66: -8.48 | H66: 0.25
B67: Change in A/P | C67: 63.58 | D67: 43.44 | E67: -56.26 | F67: -41.07 | G67: 46.78 | H67: -13.55
B68: Change in Inventory | C68: -104.62 | D68: -190.07 | E68: -77.19 | F68: 47.27 | G68: -268.57 | H68: 213.78
B69: Change in Other Assets/Liabilities | C69: -55.26 | D69: -133.67 | E69: -363.1 | F69: -266.98 | G69: -184.27 | H69: -249.66
